cloud_validol/__init__.py
cloud_validol/loader/__init__.py
cloud_validol/loader/main.py
cloud_validol/loader/lib/__init__.py
cloud_validol/loader/lib/cot.py
cloud_validol/loader/lib/interval_utils.py
cloud_validol/loader/lib/pg.py
cloud_validol/loader/reports/__init__.py
cloud_validol/loader/reports/cftc.py
cloud_validol/loader/reports/ice.py
cloud_validol/loader/reports/moex.py
cloud_validol/loader/reports/monetary.py
cloud_validol/loader/reports/prices.py
cloud_validol/postgresql/pgmigrate/migrations/V01__initial_schema.sql
cloud_validol-0.2.3.dist-info/METADATA
cloud_validol-0.2.3.dist-info/WHEEL
cloud_validol-0.2.3.dist-info/entry_points.txt
cloud_validol-0.2.3.dist-info/top_level.txt
cloud_validol-0.2.3.dist-info/RECORD
